[{"UniqueCarrier":"9E","count":2310,"Code":"9E","Description":"Pinnacle Airlines Inc."},{"UniqueCarrier":"AA","count":116177,"Code":"AA","Description":"American Airlines Inc."},{"UniqueCarrier":"AS","count":3043,"Code":"AS","Description":"Alaska Airlines Inc."},{"UniqueCarrier":"B6","count":51605,"Code":"B6","Description":"JetBlue Airways"},{"UniqueCarrier":"CO","count":83244,"Code":"CO","Description":"Continental Air Lines Inc."},{"UniqueCarrier":"DH","count":4893,"Code":"DH","Description":"Independence Air"},{"UniqueCarrier":"DL","count":179997,"Code":"DL","Description":"Delta Air Lines Inc."},{"UniqueCarrier":"EA","count":33926,"Code":"EA","Description":"Eastern Air Lines Inc."},{"UniqueCarrier":"EV","count":99,"Code":"EV","Description":"Atlantic Southeast Airlines"},{"UniqueCarrier":"FL","count":29137,"Code":"FL","Description":"AirTran Airways Corporation"},{"UniqueCarrier":"HP","count":12871,"Code":"HP","Description":"America West Airlines Inc. (Merged with US Airways 9\/05. Stopped reporting 10\/07.)"},{"UniqueCarrier":"ML 1","count":2482,"Code":"ML 1","Description":"Midway Airlines Inc. (1)"},{"UniqueCarrier":"MQ","count":55470,"Code":"MQ","Description":"American Eagle Airlines Inc."},{"UniqueCarrier":"NW","count":65914,"Code":"NW","Description":"Northwest Airlines Inc."},{"UniqueCarrier":"OH","count":47114,"Code":"OH","Description":"Comair Inc."},{"UniqueCarrier":"PA 1","count":22772,"Code":"PA 1","Description":"Pan American World Airways (1)"},{"UniqueCarrier":"PI","count":19493,"Code":"PI","Description":"Piedmont Aviation Inc."},{"UniqueCarrier":"TW","count":17267,"Code":"TW","Description":"Trans World Airways LLC"},{"UniqueCarrier":"TZ","count":2269,"Code":"TZ","Description":"ATA Airlines d\/b\/a ATA"},{"UniqueCarrier":"UA","count":93694,"Code":"UA","Description":"United Air Lines Inc."},{"UniqueCarrier":"US","count":208924,"Code":"US","Description":"US Airways Inc. (Merged with America West 9\/05. Reporting for both starting 10\/07.)"},{"UniqueCarrier":"XE","count":1729,"Code":"XE","Description":"Expressjet Airlines Inc."},{"UniqueCarrier":"YV","count":953,"Code":"YV","Description":"Mesa Airlines Inc."}]